risklab/__init__.py
risklab/backtest.py
risklab/returns.py
risklab/stats.py
risklab/volatility_targeting.py
risklab-1.0.2.dist-info/METADATA
risklab-1.0.2.dist-info/WHEEL
risklab-1.0.2.dist-info/licenses/LICENSE
risklab-1.0.2.dist-info/RECORD
